lightregistry/__init__.py
lightregistry/client.py
lightregistry/consul.py
lightregistry/http.py
lightregistry/kvstore.py
lightregistry/registry.py
lightregistry/telemetry.py
lightregistry-0.0.1.dist-info/LICENSE
lightregistry-0.0.1.dist-info/METADATA
lightregistry-0.0.1.dist-info/WHEEL
lightregistry-0.0.1.dist-info/top_level.txt
lightregistry-0.0.1.dist-info/RECORD
