Metadata-Version: 2.1
Name: lightregistry
Version: 0.0.1
Summary: Package for implementing service discovery in a really light way.
Home-page: https://github.com/goncalorafaria/lightregistry
Author: Goncalo Faria
Author-email: gfaria@cs.washington.edu
Classifier: Programming Language :: Python :: 3
Classifier: License :: OSI Approved :: MIT License
Classifier: Operating System :: OS Independent
Requires-Python: >=3.6.0
License-File: LICENSE
Requires-Dist: aiohttp
Requires-Dist: collections
Requires-Dist: asyncio
Requires-Dist: logging
